khc_cli/__init__.py
khc_cli/config.py
khc_cli/github_client.py
khc_cli/main.py
khc_cli/version.py
khc_cli/awesomecure/__init__.py
khc_cli/awesomecure/awesome2py.py
khc_cli/awesomecure/md2dict.py
khc_cli/commands/__init__.py
khc_cli/commands/analyze.py
khc_cli/commands/config.py
khc_cli/commands/curate.py
khc_cli/commands/etl.py
khc_cli/resources/awesome_list_template.md
khc_cli/utils/__init__.py
khc_cli/utils/helpers.py
khc_cli/utils/template_loader.py
khc_cli-1.20.0.dist-info/METADATA
khc_cli-1.20.0.dist-info/WHEEL
khc_cli-1.20.0.dist-info/entry_points.txt
khc_cli-1.20.0.dist-info/licenses/LICENSE
khc_cli-1.20.0.dist-info/RECORD
