Metadata-Version: 2.4
Name: khc-cli
Version: 1.20.0
Summary: CLI tool for analyzing and curating awesome lists focused on sustainable and open source technologies
Project-URL: Homepage, https://github.com/aguennoune/khc-cli
Project-URL: Bug Tracker, https://github.com/aguennoune/khc-cli/issues
Project-URL: Documentation, https://khc-cli.readthedocs.io/
Author-email: Abderrahim Guennoune <aguennoune@outlook.com>
License: MIT License
License-File: LICENSE
Keywords: analysis,awesome-list,cli,curation,github,open-source,sustainability,technology
Classifier: Environment :: Console
Classifier: Intended Audience :: Developers
Classifier: Intended Audience :: Information Technology
Classifier: Intended Audience :: Science/Research
Classifier: License :: OSI Approved :: MIT License
Classifier: Operating System :: OS Independent
Classifier: Programming Language :: Python :: 3
Classifier: Programming Language :: Python :: 3.10
Classifier: Programming Language :: Python :: 3.11
Classifier: Topic :: Software Development :: Libraries :: Python Modules
Classifier: Topic :: Utilities
Requires-Python: <4.0,>=3.10
Requires-Dist: beautifulsoup4>=4.12.2
Requires-Dist: markdown>=3.8
Requires-Dist: pygithub>=2.1.1
Requires-Dist: python-dotenv>=1.0.0
Requires-Dist: pyyaml>=6.0.2
Requires-Dist: requests>=2.31.0
Requires-Dist: rich>=13.6.0
Requires-Dist: termcolor>=2.3.0
Requires-Dist: twine>=6.1.0
Requires-Dist: typer>=0.16.0
Requires-Dist: typing-extensions>=4.8.0
Provides-Extra: dev
Requires-Dist: black>=23.0.0; extra == 'dev'
Requires-Dist: isort>=5.12.0; extra == 'dev'
Requires-Dist: mypy>=1.3.0; extra == 'dev'
Requires-Dist: pytest-cov>=4.0.0; extra == 'dev'
Requires-Dist: pytest>=7.0.0; extra == 'dev'
Requires-Dist: ruff>=0.0.270; extra == 'dev'
Requires-Dist: sphinx-click>=4.4.0; extra == 'dev'
Requires-Dist: sphinx-rtd-theme>=1.2.0; extra == 'dev'
Requires-Dist: sphinx>=7.0.0; extra == 'dev'
Provides-Extra: docs
Requires-Dist: sphinx-click>=4.4.0; extra == 'docs'
Requires-Dist: sphinx-rtd-theme>=1.2.0; extra == 'docs'
Requires-Dist: sphinx>=7.0.0; extra == 'docs'
